ai_council/__init__.py
ai_council/cli.py
ai_council/factory.py
ai_council/main.py
ai_council/analysis/__init__.py
ai_council/analysis/decomposer.py
ai_council/analysis/engine.py
ai_council/arbitration/__init__.py
ai_council/arbitration/layer.py
ai_council/core/__init__.py
ai_council/core/failure_handling.py
ai_council/core/interfaces.py
ai_council/core/models.py
ai_council/core/timeout_handler.py
ai_council/execution/__init__.py
ai_council/execution/agent.py
ai_council/execution/mock_models.py
ai_council/orchestration/__init__.py
ai_council/orchestration/cost_optimizer.py
ai_council/orchestration/layer.py
ai_council/routing/__init__.py
ai_council/routing/context_protocol.py
ai_council/routing/registry.py
ai_council/synthesis/__init__.py
ai_council/synthesis/layer.py
ai_council/utils/__init__.py
ai_council/utils/config.py
ai_council/utils/config_builder.py
ai_council/utils/logging.py
ai_council/utils/plugin_manager.py
ai_council_orchestrator-1.0.0.dist-info/licenses/LICENSE
ai_council_orchestrator-1.0.0.dist-info/METADATA
ai_council_orchestrator-1.0.0.dist-info/WHEEL
ai_council_orchestrator-1.0.0.dist-info/top_level.txt
ai_council_orchestrator-1.0.0.dist-info/RECORD
