Metadata-Version: 2.4
Name: ai-council-orchestrator
Version: 1.0.0
Summary: A production-grade multi-agent AI orchestration system that intelligently coordinates multiple AI models
Author-email: Shriyash <shriyash@example.com>
Maintainer: AI Council Team
License: MIT
Project-URL: Homepage, https://github.com/shrixtacy/Ai-Council
Project-URL: Repository, https://github.com/shrixtacy/Ai-Council
Project-URL: Documentation, https://github.com/shrixtacy/Ai-Council/tree/master/docs
Project-URL: Bug Tracker, https://github.com/shrixtacy/Ai-Council/issues
Project-URL: Source Code, https://github.com/shrixtacy/Ai-Council
Project-URL: Download, https://pypi.org/project/ai-council/
Keywords: ai,orchestration,multi-agent,llm,coordination,artificial-intelligence,machine-learning,ai-models
Classifier: Development Status :: 5 - Production/Stable
Classifier: Intended Audience :: Developers
Classifier: Intended Audience :: Science/Research
Classifier: License :: OSI Approved :: MIT License
Classifier: Operating System :: OS Independent
Classifier: Programming Language :: Python :: 3
Classifier: Programming Language :: Python :: 3.8
Classifier: Programming Language :: Python :: 3.9
Classifier: Programming Language :: Python :: 3.10
Classifier: Programming Language :: Python :: 3.11
Classifier: Programming Language :: Python :: 3.12
Classifier: Topic :: Scientific/Engineering :: Artificial Intelligence
Classifier: Topic :: Software Development :: Libraries :: Python Modules
Classifier: Topic :: System :: Distributed Computing
Requires-Python: >=3.8
License-File: LICENSE
Requires-Dist: pydantic>=2.0.0
Requires-Dist: structlog>=23.0.0
Requires-Dist: pyyaml>=6.0
Requires-Dist: httpx>=0.24.0
Requires-Dist: tenacity>=8.0.0
Requires-Dist: typing-extensions>=4.0.0
Provides-Extra: dev
Requires-Dist: pytest>=7.0.0; extra == "dev"
Requires-Dist: pytest-asyncio>=0.21.0; extra == "dev"
Requires-Dist: pytest-cov>=4.0.0; extra == "dev"
Requires-Dist: hypothesis>=6.0.0; extra == "dev"
Requires-Dist: black>=23.0.0; extra == "dev"
Requires-Dist: isort>=5.0.0; extra == "dev"
Requires-Dist: flake8>=6.0.0; extra == "dev"
Requires-Dist: mypy>=1.0.0; extra == "dev"
Requires-Dist: pre-commit>=3.0.0; extra == "dev"
Provides-Extra: test
Requires-Dist: pytest>=7.0.0; extra == "test"
Requires-Dist: pytest-asyncio>=0.21.0; extra == "test"
Requires-Dist: pytest-cov>=4.0.0; extra == "test"
Requires-Dist: hypothesis>=6.0.0; extra == "test"
Dynamic: license-file
